{"nodes": [{"id": "midea_stock", "label": "\u7f8e\u7684\u96c6\u56e2 (000333)", "file_type": "document", "source_file": "docs/stock-analytics/sectors/consumer/home-appliance/2026-06-13-\u7f8e\u7684\u96c6\u56e2-buffett\u5206\u6790.md", "source_location": null, "source_url": null, "captured_at": "2026-06-13", "author": null, "contributor": null}, {"id": "midea_rating_config", "label": "\u7f8e\u7684 rating: config", "file_type": "document", "source_file": "docs/stock-analytics/sectors/consumer/home-appliance/2026-06-13-\u7f8e\u7684\u96c6\u56e2-buffett\u5206\u6790.md", "source_location": null, "source_url": null, "captured_at": "2026-06-13", "author": null, "contributor": null}, {"id": "midea_rationale_cash_cow_slightly_pricey", "label": "\u767d\u7535\u9f99\u5934+\u9ad8\u5206\u7ea2\u73b0\u91d1\u725b\u4f46Q1\u6263\u975e-14%\u5185\u9500\u89c1\u9876\u5b89\u5168\u8fb9\u9645-2.3%\u505a\u5e95\u4ed3", "file_type": "document", "source_file": "docs/stock-analytics/sectors/consumer/home-appliance/2026-06-13-\u7f8e\u7684\u96c6\u56e2-buffett\u5206\u6790.md", "source_location": null, "source_url": null, "captured_at": "2026-06-13", "author": null, "contributor": null}, {"id": "theme_obm_overseas_appliance", "label": "\u767d\u7535\u51fa\u6d77OBM\u4e3b\u9898", "file_type": "document", "source_file": "docs/stock-analytics/sectors/consumer/home-appliance/2026-06-13-\u7f8e\u7684\u96c6\u56e2-buffett\u5206\u6790.md", "source_location": null, "source_url": null, "captured_at": null, "author": null, "contributor": null}], "edges": [{"source": "midea_rating_config", "target": "midea_stock", "relation": "conceptually_related_to", "confidence": "EXTRACTED", "confidence_score": 1.0, "source_file": "docs/stock-analytics/sectors/consumer/home-appliance/2026-06-13-\u7f8e\u7684\u96c6\u56e2-buffett\u5206\u6790.md", "source_location": null, "weight": 1.0}, {"source": "midea_rationale_cash_cow_slightly_pricey", "target": "midea_rating_config", "relation": "rationale_for", "confidence": "EXTRACTED", "confidence_score": 1.0, "source_file": "docs/stock-analytics/sectors/consumer/home-appliance/2026-06-13-\u7f8e\u7684\u96c6\u56e2-buffett\u5206\u6790.md", "source_location": null, "weight": 1.0}, {"source": "midea_stock", "target": "theme_obm_overseas_appliance", "relation": "conceptually_related_to", "confidence": "EXTRACTED", "confidence_score": 1.0, "source_file": "docs/stock-analytics/sectors/consumer/home-appliance/2026-06-13-\u7f8e\u7684\u96c6\u56e2-buffett\u5206\u6790.md", "source_location": null, "weight": 1.0}, {"source": "midea_stock", "target": "haier_stock", "relation": "references", "confidence": "EXTRACTED", "confidence_score": 1.0, "source_file": "docs/stock-analytics/sectors/consumer/home-appliance/2026-06-13-\u7f8e\u7684\u96c6\u56e2-buffett\u5206\u6790.md", "source_location": null, "weight": 1.0}, {"source": "midea_stock", "target": "haier_stock", "relation": "semantically_similar_to", "confidence": "INFERRED", "confidence_score": 0.9, "source_file": "docs/stock-analytics/sectors/consumer/home-appliance/2026-06-13-\u7f8e\u7684\u96c6\u56e2-buffett\u5206\u6790.md", "source_location": null, "weight": 0.9}], "hyperedges": []}