{"nodes": [{"id": "comps_\u5564\u9152\u677f\u5757_2026_04_26", "label": "\u5564\u9152\u677f\u5757 A\u80a1\u540c\u4e1acomps", "file_type": "document", "source_file": "docs/stock-analytics/comps/quarterly/26q1/2026-04-26-\u5564\u9152\u677f\u5757-comps-\u6210\u957f\u6027\u4e0e\u6295\u8d44\u51b3\u7b56.md", "source_location": null, "source_url": null, "captured_at": null, "author": null, "contributor": null}, {"id": "stock_600600_\u9752\u5c9b\u5564\u9152", "label": "\u9752\u5c9b\u5564\u9152 (600600)", "file_type": "document", "source_file": "docs/stock-analytics/comps/quarterly/26q1/2026-04-26-\u5564\u9152\u677f\u5757-comps-\u6210\u957f\u6027\u4e0e\u6295\u8d44\u51b3\u7b56.md", "source_location": null, "source_url": null, "captured_at": null, "author": null, "contributor": null}, {"id": "stock_600132_\u91cd\u5e86\u5564\u9152", "label": "\u91cd\u5e86\u5564\u9152 (600132)", "file_type": "document", "source_file": "docs/stock-analytics/comps/quarterly/26q1/2026-04-26-\u5564\u9152\u677f\u5757-comps-\u6210\u957f\u6027\u4e0e\u6295\u8d44\u51b3\u7b56.md", "source_location": null, "source_url": null, "captured_at": null, "author": null, "contributor": null}, {"id": "stock_000729_\u71d5\u4eac\u5564\u9152", "label": "\u71d5\u4eac\u5564\u9152 (000729)", "file_type": "document", "source_file": "docs/stock-analytics/comps/quarterly/26q1/2026-04-26-\u5564\u9152\u677f\u5757-comps-\u6210\u957f\u6027\u4e0e\u6295\u8d44\u51b3\u7b56.md", "source_location": null, "source_url": null, "captured_at": null, "author": null, "contributor": null}, {"id": "stock_000929_\u5170\u5dde\u9ec4\u6cb3", "label": "*ST \u5170\u9ec4 (000929)", "file_type": "document", "source_file": "docs/stock-analytics/comps/quarterly/26q1/2026-04-26-\u5564\u9152\u677f\u5757-comps-\u6210\u957f\u6027\u4e0e\u6295\u8d44\u51b3\u7b56.md", "source_location": null, "source_url": null, "captured_at": null, "author": null, "contributor": null}], "edges": [{"source": "comps_\u5564\u9152\u677f\u5757_2026_04_26", "target": "stock_600600_\u9752\u5c9b\u5564\u9152", "relation": "references", "confidence": "EXTRACTED", "confidence_score": 1.0, "source_file": "docs/stock-analytics/comps/quarterly/26q1/2026-04-26-\u5564\u9152\u677f\u5757-comps-\u6210\u957f\u6027\u4e0e\u6295\u8d44\u51b3\u7b56.md", "source_location": null, "weight": 1.0}, {"source": "comps_\u5564\u9152\u677f\u5757_2026_04_26", "target": "stock_600132_\u91cd\u5e86\u5564\u9152", "relation": "references", "confidence": "EXTRACTED", "confidence_score": 1.0, "source_file": "docs/stock-analytics/comps/quarterly/26q1/2026-04-26-\u5564\u9152\u677f\u5757-comps-\u6210\u957f\u6027\u4e0e\u6295\u8d44\u51b3\u7b56.md", "source_location": null, "weight": 1.0}, {"source": "comps_\u5564\u9152\u677f\u5757_2026_04_26", "target": "stock_000729_\u71d5\u4eac\u5564\u9152", "relation": "references", "confidence": "EXTRACTED", "confidence_score": 1.0, "source_file": "docs/stock-analytics/comps/quarterly/26q1/2026-04-26-\u5564\u9152\u677f\u5757-comps-\u6210\u957f\u6027\u4e0e\u6295\u8d44\u51b3\u7b56.md", "source_location": null, "weight": 1.0}, {"source": "comps_\u5564\u9152\u677f\u5757_2026_04_26", "target": "stock_000929_\u5170\u5dde\u9ec4\u6cb3", "relation": "references", "confidence": "EXTRACTED", "confidence_score": 1.0, "source_file": "docs/stock-analytics/comps/quarterly/26q1/2026-04-26-\u5564\u9152\u677f\u5757-comps-\u6210\u957f\u6027\u4e0e\u6295\u8d44\u51b3\u7b56.md", "source_location": null, "weight": 1.0}], "hyperedges": []}