{"nodes": [{"id": "test_esports_routing", "label": "Esports Daily Schedule routing tests", "file_type": "code", "source_file": "tests/test_esports_daily_schedule_routing.py", "source_location": null, "source_url": null, "captured_at": null, "author": null, "contributor": null}], "edges": [{"source": "test_esports_routing", "target": "esports_daily_strategy", "relation": "references", "confidence": "EXTRACTED", "confidence_score": 1.0, "source_file": "tests/test_esports_daily_schedule_routing.py", "source_location": "L14", "weight": 1.0}, {"source": "test_esports_routing", "target": "esports_retry_queue", "relation": "references", "confidence": "EXTRACTED", "confidence_score": 1.0, "source_file": "tests/test_esports_daily_schedule_routing.py", "source_location": "L13", "weight": 1.0}], "hyperedges": []}