{"nodes": [{"id": "trade_stats_html", "label": "trade_stats.html (\u4ea4\u6613\u7edf\u8ba1)", "file_type": "code", "source_file": "app/templates/trade_stats.html", "source_location": null, "source_url": null, "captured_at": null, "author": null, "contributor": null}], "edges": [{"source": "trade_stats_html", "target": "base_html_template", "relation": "references", "confidence": "EXTRACTED", "confidence_score": 1.0, "source_file": "app/templates/trade_stats.html", "source_location": "line 1", "weight": 1.0}, {"source": "trade_stats_html", "target": "trade_stats_js", "relation": "references", "confidence": "EXTRACTED", "confidence_score": 1.0, "source_file": "app/templates/trade_stats.html", "source_location": "line 159", "weight": 1.0}, {"source": "trade_stats_html", "target": "trade_index_endpoint", "relation": "references", "confidence": "EXTRACTED", "confidence_score": 1.0, "source_file": "app/templates/trade_stats.html", "source_location": "url_for('trade.index')", "weight": 1.0}], "hyperedges": []}