{"nodes": [{"id": "doc_\u81f3\u7eaf\u79d1\u6280", "label": "\u81f3\u7eaf\u79d1\u6280 \u534a\u5bfc\u4f53\u5de5\u827a\u7cfb\u7edf buffett\u5206\u6790", "file_type": "document", "source_file": "docs/stock-analytics/sectors/semiconductor/process-systems/2026-06-28-\u81f3\u7eaf\u79d1\u6280-buffett\u5206\u6790.md", "source_location": null, "source_url": null, "captured_at": null, "author": null, "contributor": null}, {"id": "zhichun_603690", "label": "\u81f3\u7eaf\u79d1\u6280(603690) buffett\u5206\u6790 \u2014 \u9ad8\u7eaf\u5de5\u827a\u7cfb\u7edf\u96c6\u6210/\u56f0\u5883\u53cd\u8f6c", "file_type": "document", "source_file": "docs/stock-analytics/sectors/semiconductor/process-systems/2026-06-28-\u81f3\u7eaf\u79d1\u6280-buffett\u5206\u6790.md", "source_location": null, "source_url": null, "captured_at": "2026-06-28", "author": null, "contributor": null}, {"id": "rat_zhichun", "label": "rationale:\u9ad8\u7eaf\u5de5\u827a\u7cfb\u7edf\u96c6\u6210\u5546\u56f0\u5883\u53cd\u8f6c\u547d\u9898,\u8ba2\u5355\u5411\u597d\u4f462025\u5de8\u4e8f7.77\u4ebf/\u6263\u975e3\u5e74\u8d1f/\u8d22\u52a1\u8106\u5f31,\u5b89\u5168\u8fb9\u9645-39%\u2192watch", "file_type": "document", "source_file": "docs/stock-analytics/sectors/semiconductor/process-systems/2026-06-28-\u81f3\u7eaf\u79d1\u6280-buffett\u5206\u6790.md", "source_location": null, "source_url": null, "captured_at": null, "author": null, "contributor": null}, {"id": "zhichun_buffett", "label": "\u81f3\u7eaf\u79d1\u6280-buffett\u5206\u6790", "file_type": "document", "source_file": "docs/stock-analytics/sectors/semiconductor/process-systems/2026-06-28-\u81f3\u7eaf\u79d1\u6280-buffett\u5206\u6790.md", "source_location": null, "source_url": null, "captured_at": null, "author": null, "contributor": null}], "edges": [{"source": "rat_zhichun", "target": "zhichun_603690", "relation": "rationale_for", "confidence": "EXTRACTED", "confidence_score": 1.0, "source_file": "docs/stock-analytics/sectors/semiconductor/process-systems/2026-06-28-\u81f3\u7eaf\u79d1\u6280-buffett\u5206\u6790.md", "source_location": null, "weight": 1.0}], "hyperedges": []}