{"nodes": [{"id": "huatian_002185_q1", "label": "\u534e\u5929\u79d1\u6280 26Q1 \u5b63\u62a5\u70b9\u8bc4", "file_type": "document", "source_file": "docs/analysis/26q1/2026-04-29-\u534e\u5929\u79d1\u6280-26Q1\u5b63\u62a5\u70b9\u8bc4.md", "source_location": null, "source_url": null, "captured_at": "2026-04-29", "author": null, "contributor": null}, {"id": "huatian_002185", "label": "\u534e\u5929\u79d1\u6280 (002185)", "file_type": "document", "source_file": "docs/analysis/26q1/2026-04-29-\u534e\u5929\u79d1\u6280-26Q1\u5b63\u62a5\u70b9\u8bc4.md", "source_location": null, "source_url": null, "captured_at": "2026-04-29", "author": null, "contributor": null}, {"id": "concept_low_quality_expansion", "label": "\u4ee5\u4ef7\u6362\u91cf\u7684\u4f4e\u8d28\u91cf\u6269\u5f20", "file_type": "document", "source_file": "docs/analysis/26q1/2026-04-29-\u534e\u5929\u79d1\u6280-26Q1\u5b63\u62a5\u70b9\u8bc4.md", "source_location": null, "source_url": null, "captured_at": "2026-04-29", "author": null, "contributor": null}], "edges": [{"source": "huatian_002185_q1", "target": "huatian_002185", "relation": "references", "confidence": "EXTRACTED", "confidence_score": 1.0, "source_file": "docs/analysis/26q1/2026-04-29-\u534e\u5929\u79d1\u6280-26Q1\u5b63\u62a5\u70b9\u8bc4.md", "source_location": null, "weight": 1.0}, {"source": "huatian_002185", "target": "theme_cpu_pcb", "relation": "conceptually_related_to", "confidence": "EXTRACTED", "confidence_score": 1.0, "source_file": "docs/analysis/26q1/2026-04-29-\u534e\u5929\u79d1\u6280-26Q1\u5b63\u62a5\u70b9\u8bc4.md", "source_location": null, "weight": 1.0}, {"source": "concept_low_quality_expansion", "target": "huatian_002185_q1", "relation": "rationale_for", "confidence": "EXTRACTED", "confidence_score": 1.0, "source_file": "docs/analysis/26q1/2026-04-29-\u534e\u5929\u79d1\u6280-26Q1\u5b63\u62a5\u70b9\u8bc4.md", "source_location": null, "weight": 1.0}, {"source": "huatian_002185_q1", "target": "tfme_002156_q1", "relation": "shares_data_with", "confidence": "EXTRACTED", "confidence_score": 1.0, "source_file": "docs/analysis/26q1/2026-04-29-\u534e\u5929\u79d1\u6280-26Q1\u5b63\u62a5\u70b9\u8bc4.md", "source_location": null, "weight": 1.0}, {"source": "huatian_002185_q1", "target": "longsys_301308_q1", "relation": "semantically_similar_to", "confidence": "INFERRED", "confidence_score": 0.7, "source_file": "docs/analysis/26q1/2026-04-29-\u534e\u5929\u79d1\u6280-26Q1\u5b63\u62a5\u70b9\u8bc4.md", "source_location": null, "weight": 0.7}], "hyperedges": []}