{"nodes": [{"id": "puran_company", "label": "\u666e\u5189\u80a1\u4efd (688766.SH)", "file_type": "document", "source_file": "docs/analysis/2026-04-25-\u666e\u5189\u80a1\u4efd-buffett\u5206\u6790.md", "source_location": null, "source_url": null, "captured_at": null, "author": null, "contributor": null}, {"id": "puran_ticker_688766", "label": "688766", "file_type": "document", "source_file": "docs/analysis/2026-04-25-\u666e\u5189\u80a1\u4efd-buffett\u5206\u6790.md", "source_location": null, "source_url": null, "captured_at": null, "author": null, "contributor": null}, {"id": "puran_risk_gigadevice_compete", "label": "\u5146\u6613\u53cd\u5411\u4e0b\u6c89 NOR \u4e2d\u4f4e\u7aef\u4ef7\u683c\u6218\u98ce\u9669", "file_type": "document", "source_file": "docs/analysis/2026-04-25-\u666e\u5189\u80a1\u4efd-buffett\u5206\u6790.md", "source_location": null, "source_url": null, "captured_at": null, "author": null, "contributor": null}], "edges": [{"source": "puran_ticker_688766", "target": "puran_company", "relation": "ticker_of", "confidence": "EXTRACTED", "confidence_score": 1.0, "source_file": "docs/analysis/2026-04-25-\u666e\u5189\u80a1\u4efd-buffett\u5206\u6790.md", "source_location": null, "weight": 1.0}, {"source": "puran_risk_gigadevice_compete", "target": "puran_company", "relation": "rationale_for", "confidence": "EXTRACTED", "confidence_score": 0.95, "source_file": "docs/analysis/2026-04-25-\u666e\u5189\u80a1\u4efd-buffett\u5206\u6790.md", "source_location": null, "weight": 1.0}, {"source": "puran_company", "target": "sector_semi_storage", "relation": "belongs_to", "confidence": "EXTRACTED", "confidence_score": 1.0, "source_file": "docs/analysis/2026-04-25-\u666e\u5189\u80a1\u4efd-buffett\u5206\u6790.md", "source_location": null, "weight": 1.0}, {"source": "puran_company", "target": "concept_circle_of_competence", "relation": "tested_against", "confidence": "EXTRACTED", "confidence_score": 0.95, "source_file": "docs/analysis/2026-04-25-\u666e\u5189\u80a1\u4efd-buffett\u5206\u6790.md", "source_location": null, "weight": 1.0}, {"source": "puran_company", "target": "juchen_company", "relation": "conceptually_related_to", "confidence": "EXTRACTED", "confidence_score": 0.9, "source_file": "docs/analysis/2026-04-25-\u666e\u5189\u80a1\u4efd-buffett\u5206\u6790.md", "source_location": null, "weight": 1.0}], "hyperedges": []}