{"nodes": [{"id": "comps_sungrow", "label": "comps \u9633\u5149\u7535\u6e90\u6210\u957f\u6027\u4e0e\u6295\u8d44\u51b3\u7b56", "file_type": "document", "source_file": "docs/stock-analytics/comps/quarterly/26q1/2026-04-28-\u9633\u5149\u7535\u6e90-comps-\u6210\u957f\u6027\u4e0e\u6295\u8d44\u51b3\u7b56.md", "source_location": null, "source_url": null, "captured_at": "2026-04-28", "author": null, "contributor": null}, {"id": "stock_sungrow", "label": "\u9633\u5149\u7535\u6e90 300274", "file_type": "document", "source_file": "docs/stock-analytics/comps/quarterly/26q1/2026-04-28-\u9633\u5149\u7535\u6e90-comps-\u6210\u957f\u6027\u4e0e\u6295\u8d44\u51b3\u7b56.md", "source_location": null, "source_url": null, "captured_at": null, "author": null, "contributor": null}, {"id": "stock_deye", "label": "\u5fb7\u4e1a\u80a1\u4efd 605117", "file_type": "document", "source_file": "docs/stock-analytics/comps/quarterly/26q1/2026-04-28-\u9633\u5149\u7535\u6e90-comps-\u6210\u957f\u6027\u4e0e\u6295\u8d44\u51b3\u7b56.md", "source_location": null, "source_url": null, "captured_at": null, "author": null, "contributor": null}, {"id": "theme_solar_storage", "label": "\u4e3b\u9898 \u5149\u4f0f\u9006\u53d8\u5668/\u50a8\u80fd", "file_type": "document", "source_file": "docs/stock-analytics/comps/quarterly/26q1/2026-04-28-\u9633\u5149\u7535\u6e90-comps-\u6210\u957f\u6027\u4e0e\u6295\u8d44\u51b3\u7b56.md", "source_location": null, "source_url": null, "captured_at": null, "author": null, "contributor": null}, {"id": "rationale_sungrow_dual_optimal", "label": "\u8bba\u70b9 \u9633\u5149\u57fa\u672c\u9762+\u4f30\u503c\u53cc\u4f18(PEG0.43)\u8d5b\u9053\u552f\u4e00", "file_type": "document", "source_file": "docs/stock-analytics/comps/quarterly/26q1/2026-04-28-\u9633\u5149\u7535\u6e90-comps-\u6210\u957f\u6027\u4e0e\u6295\u8d44\u51b3\u7b56.md", "source_location": "\u7ed3\u8bba\u901f\u89c8", "source_url": null, "captured_at": null, "author": null, "contributor": null}], "edges": [{"source": "comps_sungrow", "target": "theme_solar_storage", "relation": "conceptually_related_to", "confidence": "EXTRACTED", "confidence_score": 1.0, "source_file": "docs/stock-analytics/comps/quarterly/26q1/2026-04-28-\u9633\u5149\u7535\u6e90-comps-\u6210\u957f\u6027\u4e0e\u6295\u8d44\u51b3\u7b56.md", "source_location": "themes", "weight": 1.0}, {"source": "comps_sungrow", "target": "stock_sungrow", "relation": "cites", "confidence": "EXTRACTED", "confidence_score": 1.0, "source_file": "docs/stock-analytics/comps/quarterly/26q1/2026-04-28-\u9633\u5149\u7535\u6e90-comps-\u6210\u957f\u6027\u4e0e\u6295\u8d44\u51b3\u7b56.md", "source_location": "\u7ed3\u8bba\u901f\u89c8", "weight": 1.0}, {"source": "comps_sungrow", "target": "stock_deye", "relation": "cites", "confidence": "EXTRACTED", "confidence_score": 1.0, "source_file": "docs/stock-analytics/comps/quarterly/26q1/2026-04-28-\u9633\u5149\u7535\u6e90-comps-\u6210\u957f\u6027\u4e0e\u6295\u8d44\u51b3\u7b56.md", "source_location": "\u7ed3\u8bba\u901f\u89c8", "weight": 1.0}, {"source": "comps_sungrow", "target": "rationale_sungrow_dual_optimal", "relation": "references", "confidence": "EXTRACTED", "confidence_score": 1.0, "source_file": "docs/stock-analytics/comps/quarterly/26q1/2026-04-28-\u9633\u5149\u7535\u6e90-comps-\u6210\u957f\u6027\u4e0e\u6295\u8d44\u51b3\u7b56.md", "source_location": "\u6838\u5fc3\u5224\u65ad", "weight": 1.0}, {"source": "rationale_sungrow_dual_optimal", "target": "stock_sungrow", "relation": "rationale_for", "confidence": "EXTRACTED", "confidence_score": 1.0, "source_file": "docs/stock-analytics/comps/quarterly/26q1/2026-04-28-\u9633\u5149\u7535\u6e90-comps-\u6210\u957f\u6027\u4e0e\u6295\u8d44\u51b3\u7b56.md", "source_location": "\u4f18\u5148\u89c2\u5bdf", "weight": 1.0}, {"source": "comps_sungrow", "target": "buffett_sungrow_ext", "relation": "references", "confidence": "AMBIGUOUS", "confidence_score": 0.2, "source_file": "docs/stock-analytics/comps/quarterly/26q1/2026-04-28-\u9633\u5149\u7535\u6e90-comps-\u6210\u957f\u6027\u4e0e\u6295\u8d44\u51b3\u7b56.md", "source_location": "related_docs (out of chunk)", "weight": 1.0}, {"source": "stock_sungrow", "target": "stock_deye", "relation": "semantically_similar_to", "confidence": "INFERRED", "confidence_score": 0.7, "source_file": "docs/stock-analytics/comps/quarterly/26q1/2026-04-28-\u9633\u5149\u7535\u6e90-comps-\u6210\u957f\u6027\u4e0e\u6295\u8d44\u51b3\u7b56.md", "source_location": "\u50a8\u80fd\u53cc\u9f99\u5934", "weight": 1.0}], "hyperedges": []}