{"nodes": [{"id": "watch_html", "label": "watch.html \u76ef\u76d8\u6a21\u677f", "file_type": "code", "source_file": "app/templates/watch.html", "source_location": null, "source_url": null, "captured_at": null, "author": null, "contributor": null}, {"id": "mod_watch_template", "label": "app/templates/watch.html", "file_type": "code", "source_file": "app/templates/watch.html", "source_location": null, "source_url": null, "captured_at": null, "author": null, "contributor": null}], "edges": [{"source": "watch_html", "target": "base_html", "relation": "references", "confidence": "EXTRACTED", "confidence_score": 1.0, "source_file": "app/templates/watch.html", "source_location": null, "weight": 1.0}], "hyperedges": []}