{"nodes": [{"id": "d_git_stock_tests_test_alert_removed_py", "label": "test_alert_removed.py", "file_type": "code", "source_file": "D:\\Git\\stock\\tests\\test_alert_removed.py", "source_location": "L1"}, {"id": "tests_test_alert_removed_test_alert_bp_not_exported", "label": "test_alert_bp_not_exported()", "file_type": "code", "source_file": "D:\\Git\\stock\\tests\\test_alert_removed.py", "source_location": "L5"}, {"id": "tests_test_alert_removed_test_alert_module_gone", "label": "test_alert_module_gone()", "file_type": "code", "source_file": "D:\\Git\\stock\\tests\\test_alert_removed.py", "source_location": "L11"}, {"id": "tests_test_alert_removed_test_backtest_service_present", "label": "test_backtest_service_present()", "file_type": "code", "source_file": "D:\\Git\\stock\\tests\\test_alert_removed.py", "source_location": "L16"}, {"id": "tests_test_alert_removed_rationale_17", "label": "backtest.py \u88ab stock_detail \u7684 wyckoff \u56de\u6d4b\u7aef\u70b9\u4f7f\u7528\uff0c\u4e0d\u5e94\u968f alert \u9875\u5220\u9664\u3002", "file_type": "rationale", "source_file": "D:\\Git\\stock\\tests\\test_alert_removed.py", "source_location": "L17"}], "edges": [{"source": "d_git_stock_tests_test_alert_removed_py", "target": "importlib", "relation": "imports", "context": "import", "confidence": "EXTRACTED", "source_file": "D:\\Git\\stock\\tests\\test_alert_removed.py", "source_location": "L1", "weight": 1.0}, {"source": "d_git_stock_tests_test_alert_removed_py", "target": "pytest", "relation": "imports", "context": "import", "confidence": "EXTRACTED", "source_file": "D:\\Git\\stock\\tests\\test_alert_removed.py", "source_location": "L2", "weight": 1.0}, {"source": "d_git_stock_tests_test_alert_removed_py", "target": "tests_test_alert_removed_test_alert_bp_not_exported", "relation": "contains", "confidence": "EXTRACTED", "source_file": "D:\\Git\\stock\\tests\\test_alert_removed.py", "source_location": "L5", "weight": 1.0}, {"source": "d_git_stock_tests_test_alert_removed_py", "target": "tests_test_alert_removed_test_alert_module_gone", "relation": "contains", "confidence": "EXTRACTED", "source_file": "D:\\Git\\stock\\tests\\test_alert_removed.py", "source_location": "L11", "weight": 1.0}, {"source": "d_git_stock_tests_test_alert_removed_py", "target": "tests_test_alert_removed_test_backtest_service_present", "relation": "contains", "confidence": "EXTRACTED", "source_file": "D:\\Git\\stock\\tests\\test_alert_removed.py", "source_location": "L16", "weight": 1.0}, {"source": "tests_test_alert_removed_rationale_17", "target": "tests_test_alert_removed_test_backtest_service_present", "relation": "rationale_for", "confidence": "EXTRACTED", "source_file": "D:\\Git\\stock\\tests\\test_alert_removed.py", "source_location": "L17", "weight": 1.0}], "raw_calls": [{"caller_nid": "tests_test_alert_removed_test_alert_bp_not_exported", "callee": "reload", "is_member_call": true, "source_file": "D:\\Git\\stock\\tests\\test_alert_removed.py", "source_location": "L7"}, {"caller_nid": "tests_test_alert_removed_test_alert_bp_not_exported", "callee": "hasattr", "is_member_call": false, "source_file": "D:\\Git\\stock\\tests\\test_alert_removed.py", "source_location": "L8"}, {"caller_nid": "tests_test_alert_removed_test_alert_module_gone", "callee": "raises", "is_member_call": true, "source_file": "D:\\Git\\stock\\tests\\test_alert_removed.py", "source_location": "L12"}, {"caller_nid": "tests_test_alert_removed_test_alert_module_gone", "callee": "import_module", "is_member_call": true, "source_file": "D:\\Git\\stock\\tests\\test_alert_removed.py", "source_location": "L13"}, {"caller_nid": "tests_test_alert_removed_test_backtest_service_present", "callee": "import_module", "is_member_call": true, "source_file": "D:\\Git\\stock\\tests\\test_alert_removed.py", "source_location": "L18"}, {"caller_nid": "tests_test_alert_removed_test_backtest_service_present", "callee": "hasattr", "is_member_call": false, "source_file": "D:\\Git\\stock\\tests\\test_alert_removed.py", "source_location": "L19"}]}