{"nodes": [{"id": "watch_alert_service", "label": "watch_alert_service.py", "file_type": "code", "source_file": "app\\services\\watch_alert_service.py", "source_location": "L1"}, {"id": "watch_alert_service_watchalertservice", "label": "WatchAlertService", "file_type": "code", "source_file": "app\\services\\watch_alert_service.py", "source_location": "L11"}, {"id": "watch_alert_service_watchalertservice_new", "label": ".__new__()", "file_type": "code", "source_file": "app\\services\\watch_alert_service.py", "source_location": "L15"}, {"id": "watch_alert_service_watchalertservice_reset_if_new_day", "label": "._reset_if_new_day()", "file_type": "code", "source_file": "app\\services\\watch_alert_service.py", "source_location": "L26"}, {"id": "watch_alert_service_watchalertservice_has_fired", "label": "._has_fired()", "file_type": "code", "source_file": "app\\services\\watch_alert_service.py", "source_location": "L36"}, {"id": "watch_alert_service_watchalertservice_mark_fired", "label": "._mark_fired()", "file_type": "code", "source_file": "app\\services\\watch_alert_service.py", "source_location": "L40"}, {"id": "watch_alert_service_watchalertservice_make_signal", "label": "._make_signal()", "file_type": "code", "source_file": "app\\services\\watch_alert_service.py", "source_location": "L44"}, {"id": "watch_alert_service_watchalertservice_check_alerts", "label": ".check_alerts()", "file_type": "code", "source_file": "app\\services\\watch_alert_service.py", "source_location": "L53"}, {"id": "watch_alert_service_watchalertservice_check_intraday_extreme", "label": "._check_intraday_extreme()", "file_type": "code", "source_file": "app\\services\\watch_alert_service.py", "source_location": "L94"}, {"id": "watch_alert_service_watchalertservice_check_target_price", "label": "._check_target_price()", "file_type": "code", "source_file": "app\\services\\watch_alert_service.py", "source_location": "L142"}, {"id": "watch_alert_service_watchalertservice_check_support_resistance", "label": "._check_support_resistance()", "file_type": "code", "source_file": "app\\services\\watch_alert_service.py", "source_location": "L167"}, {"id": "watch_alert_service_watchalertservice_sr_detail", "label": "._sr_detail()", "file_type": "code", "source_file": "app\\services\\watch_alert_service.py", "source_location": "L212"}, {"id": "watch_alert_service_watchalertservice_check_ma_crossover", "label": "._check_ma_crossover()", "file_type": "code", "source_file": "app\\services\\watch_alert_service.py", "source_location": "L239"}, {"id": "watch_alert_service_watchalertservice_check_volume_anomaly", "label": "._check_volume_anomaly()", "file_type": "code", "source_file": "app\\services\\watch_alert_service.py", "source_location": "L279"}, {"id": "watch_alert_service_watchalertservice_check_td_sequential", "label": "._check_td_sequential()", "file_type": "code", "source_file": "app\\services\\watch_alert_service.py", "source_location": "L323"}, {"id": "watch_alert_service_rationale_1", "label": "\u76ef\u76d8\u544a\u8b66\u670d\u52a1 \u2014 7\u79cd\u68c0\u6d4b\u5668 + \u65e5\u7ea7\u53bb\u91cd", "file_type": "rationale", "source_file": "app\\services\\watch_alert_service.py", "source_location": "L1"}, {"id": "watch_alert_service_rationale_57", "label": "\u4e3b\u68c0\u6d4b\u5165\u53e3          prices: {code: {current_price, change_percent, volume, high, low,", "file_type": "rationale", "source_file": "app\\services\\watch_alert_service.py", "source_location": "L57"}, {"id": "watch_alert_service_rationale_214", "label": "\u751f\u6210\u652f\u6491/\u963b\u529b\u544a\u8b66\u7684\u4e0a\u4e0b\u6587\uff1a\u4e0b\u4e00\u5173\u952e\u4f4d + \u8ddd\u79bb\u767e\u5206\u6bd4", "file_type": "rationale", "source_file": "app\\services\\watch_alert_service.py", "source_location": "L214"}], "edges": [{"source": "watch_alert_service", "target": "logging", "relation": "imports", "confidence": "EXTRACTED", "source_file": "app\\services\\watch_alert_service.py", "source_location": "L2", "weight": 1.0}, {"source": "watch_alert_service", "target": "os", "relation": "imports", "confidence": "EXTRACTED", "source_file": "app\\services\\watch_alert_service.py", "source_location": "L3", "weight": 1.0}, {"source": "watch_alert_service", "target": "datetime", "relation": "imports_from", "confidence": "EXTRACTED", "source_file": "app\\services\\watch_alert_service.py", "source_location": "L4", "weight": 1.0}, {"source": "watch_alert_service", "target": "app_strategies_base", "relation": "imports_from", "confidence": "EXTRACTED", "source_file": "app\\services\\watch_alert_service.py", "source_location": "L6", "weight": 1.0}, {"source": "watch_alert_service", "target": "watch_alert_service_watchalertservice", "relation": "contains", "confidence": "EXTRACTED", "source_file": "app\\services\\watch_alert_service.py", "source_location": "L11", "weight": 1.0}, {"source": "watch_alert_service_watchalertservice", "target": "watch_alert_service_watchalertservice_new", "relation": "method", "confidence": "EXTRACTED", "source_file": "app\\services\\watch_alert_service.py", "source_location": "L15", "weight": 1.0}, {"source": "watch_alert_service_watchalertservice", "target": "watch_alert_service_watchalertservice_reset_if_new_day", "relation": "method", "confidence": "EXTRACTED", "source_file": "app\\services\\watch_alert_service.py", "source_location": "L26", "weight": 1.0}, {"source": "watch_alert_service_watchalertservice", "target": "watch_alert_service_watchalertservice_has_fired", "relation": "method", "confidence": "EXTRACTED", "source_file": "app\\services\\watch_alert_service.py", "source_location": "L36", "weight": 1.0}, {"source": "watch_alert_service_watchalertservice", "target": "watch_alert_service_watchalertservice_mark_fired", "relation": "method", "confidence": "EXTRACTED", "source_file": "app\\services\\watch_alert_service.py", "source_location": "L40", "weight": 1.0}, {"source": "watch_alert_service_watchalertservice", "target": "watch_alert_service_watchalertservice_make_signal", "relation": "method", "confidence": "EXTRACTED", "source_file": "app\\services\\watch_alert_service.py", "source_location": "L44", "weight": 1.0}, {"source": "watch_alert_service_watchalertservice", "target": "watch_alert_service_watchalertservice_check_alerts", "relation": "method", "confidence": "EXTRACTED", "source_file": "app\\services\\watch_alert_service.py", "source_location": "L53", "weight": 1.0}, {"source": "watch_alert_service_watchalertservice", "target": "watch_alert_service_watchalertservice_check_intraday_extreme", "relation": "method", "confidence": "EXTRACTED", "source_file": "app\\services\\watch_alert_service.py", "source_location": "L94", "weight": 1.0}, {"source": "watch_alert_service_watchalertservice", "target": "watch_alert_service_watchalertservice_check_target_price", "relation": "method", "confidence": "EXTRACTED", "source_file": "app\\services\\watch_alert_service.py", "source_location": "L142", "weight": 1.0}, {"source": "watch_alert_service_watchalertservice", "target": "watch_alert_service_watchalertservice_check_support_resistance", "relation": "method", "confidence": "EXTRACTED", "source_file": "app\\services\\watch_alert_service.py", "source_location": "L167", "weight": 1.0}, {"source": "watch_alert_service_watchalertservice", "target": "watch_alert_service_watchalertservice_sr_detail", "relation": "method", "confidence": "EXTRACTED", "source_file": "app\\services\\watch_alert_service.py", "source_location": "L212", "weight": 1.0}, {"source": "watch_alert_service_watchalertservice", "target": "watch_alert_service_watchalertservice_check_ma_crossover", "relation": "method", "confidence": "EXTRACTED", "source_file": "app\\services\\watch_alert_service.py", "source_location": "L239", "weight": 1.0}, {"source": "watch_alert_service_watchalertservice", "target": "watch_alert_service_watchalertservice_check_volume_anomaly", "relation": "method", "confidence": "EXTRACTED", "source_file": "app\\services\\watch_alert_service.py", "source_location": "L279", "weight": 1.0}, {"source": "watch_alert_service_watchalertservice", "target": "watch_alert_service_watchalertservice_check_td_sequential", "relation": "method", "confidence": "EXTRACTED", "source_file": "app\\services\\watch_alert_service.py", "source_location": "L323", "weight": 1.0}, {"source": "watch_alert_service_watchalertservice_check_alerts", "target": "watch_alert_service_watchalertservice_reset_if_new_day", "relation": "calls", "confidence": "INFERRED", "source_file": "app\\services\\watch_alert_service.py", "source_location": "L65", "weight": 0.8}, {"source": "watch_alert_service_watchalertservice_check_alerts", "target": "watch_alert_service_watchalertservice_check_intraday_extreme", "relation": "calls", "confidence": "INFERRED", "source_file": "app\\services\\watch_alert_service.py", "source_location": "L78", "weight": 0.8}, {"source": "watch_alert_service_watchalertservice_check_alerts", "target": "watch_alert_service_watchalertservice_check_td_sequential", "relation": "calls", "confidence": "INFERRED", "source_file": "app\\services\\watch_alert_service.py", "source_location": "L82", "weight": 0.8}, {"source": "watch_alert_service_watchalertservice_check_alerts", "target": "watch_alert_service_watchalertservice_check_target_price", "relation": "calls", "confidence": "INFERRED", "source_file": "app\\services\\watch_alert_service.py", "source_location": "L86", "weight": 0.8}, {"source": "watch_alert_service_watchalertservice_check_alerts", "target": "watch_alert_service_watchalertservice_check_support_resistance", "relation": "calls", "confidence": "INFERRED", "source_file": "app\\services\\watch_alert_service.py", "source_location": "L87", "weight": 0.8}, {"source": "watch_alert_service_watchalertservice_check_alerts", "target": "watch_alert_service_watchalertservice_check_ma_crossover", "relation": "calls", "confidence": "INFERRED", "source_file": "app\\services\\watch_alert_service.py", "source_location": "L88", "weight": 0.8}, {"source": "watch_alert_service_watchalertservice_check_alerts", "target": "watch_alert_service_watchalertservice_check_volume_anomaly", "relation": "calls", "confidence": "INFERRED", "source_file": "app\\services\\watch_alert_service.py", "source_location": "L89", "weight": 0.8}, {"source": "watch_alert_service_watchalertservice_check_intraday_extreme", "target": "watch_alert_service_watchalertservice_make_signal", "relation": "calls", "confidence": "INFERRED", "source_file": "app\\services\\watch_alert_service.py", "source_location": "L121", "weight": 0.8}, {"source": "watch_alert_service_watchalertservice_check_target_price", "target": "watch_alert_service_watchalertservice_has_fired", "relation": "calls", "confidence": "INFERRED", "source_file": "app\\services\\watch_alert_service.py", "source_location": "L151", "weight": 0.8}, {"source": "watch_alert_service_watchalertservice_check_target_price", "target": "watch_alert_service_watchalertservice_make_signal", "relation": "calls", "confidence": "INFERRED", "source_file": "app\\services\\watch_alert_service.py", "source_location": "L154", "weight": 0.8}, {"source": "watch_alert_service_watchalertservice_check_target_price", "target": "watch_alert_service_watchalertservice_mark_fired", "relation": "calls", "confidence": "INFERRED", "source_file": "app\\services\\watch_alert_service.py", "source_location": "L158", "weight": 0.8}, {"source": "watch_alert_service_watchalertservice_check_support_resistance", "target": "watch_alert_service_watchalertservice_has_fired", "relation": "calls", "confidence": "INFERRED", "source_file": "app\\services\\watch_alert_service.py", "source_location": "L176", "weight": 0.8}, {"source": "watch_alert_service_watchalertservice_check_support_resistance", "target": "watch_alert_service_watchalertservice_sr_detail", "relation": "calls", "confidence": "INFERRED", "source_file": "app\\services\\watch_alert_service.py", "source_location": "L185", "weight": 0.8}, {"source": "watch_alert_service_watchalertservice_check_support_resistance", "target": "watch_alert_service_watchalertservice_make_signal", "relation": "calls", "confidence": "INFERRED", "source_file": "app\\services\\watch_alert_service.py", "source_location": "L186", "weight": 0.8}, {"source": "watch_alert_service_watchalertservice_check_support_resistance", "target": "watch_alert_service_watchalertservice_mark_fired", "relation": "calls", "confidence": "INFERRED", "source_file": "app\\services\\watch_alert_service.py", "source_location": "L190", "weight": 0.8}, {"source": "watch_alert_service_watchalertservice_check_ma_crossover", "target": "watch_alert_service_watchalertservice_has_fired", "relation": "calls", "confidence": "INFERRED", "source_file": "app\\services\\watch_alert_service.py", "source_location": "L262", "weight": 0.8}, {"source": "watch_alert_service_watchalertservice_check_ma_crossover", "target": "watch_alert_service_watchalertservice_make_signal", "relation": "calls", "confidence": "INFERRED", "source_file": "app\\services\\watch_alert_service.py", "source_location": "L267", "weight": 0.8}, {"source": "watch_alert_service_watchalertservice_check_ma_crossover", "target": "watch_alert_service_watchalertservice_mark_fired", "relation": "calls", "confidence": "INFERRED", "source_file": "app\\services\\watch_alert_service.py", "source_location": "L271", "weight": 0.8}, {"source": "watch_alert_service_watchalertservice_check_volume_anomaly", "target": "watch_alert_service_watchalertservice_has_fired", "relation": "calls", "confidence": "INFERRED", "source_file": "app\\services\\watch_alert_service.py", "source_location": "L288", "weight": 0.8}, {"source": "watch_alert_service_watchalertservice_check_volume_anomaly", "target": "watch_alert_service_watchalertservice_mark_fired", "relation": "calls", "confidence": "INFERRED", "source_file": "app\\services\\watch_alert_service.py", "source_location": "L295", "weight": 0.8}, {"source": "watch_alert_service_watchalertservice_check_volume_anomaly", "target": "watch_alert_service_watchalertservice_make_signal", "relation": "calls", "confidence": "INFERRED", "source_file": "app\\services\\watch_alert_service.py", "source_location": "L316", "weight": 0.8}, {"source": "watch_alert_service_watchalertservice_check_td_sequential", "target": "watch_alert_service_watchalertservice_has_fired", "relation": "calls", "confidence": "INFERRED", "source_file": "app\\services\\watch_alert_service.py", "source_location": "L332", "weight": 0.8}, {"source": "watch_alert_service_watchalertservice_check_td_sequential", "target": "watch_alert_service_watchalertservice_make_signal", "relation": "calls", "confidence": "INFERRED", "source_file": "app\\services\\watch_alert_service.py", "source_location": "L336", "weight": 0.8}, {"source": "watch_alert_service_watchalertservice_check_td_sequential", "target": "watch_alert_service_watchalertservice_mark_fired", "relation": "calls", "confidence": "INFERRED", "source_file": "app\\services\\watch_alert_service.py", "source_location": "L340", "weight": 0.8}, {"source": "watch_alert_service_rationale_1", "target": "watch_alert_service", "relation": "rationale_for", "confidence": "EXTRACTED", "source_file": "app\\services\\watch_alert_service.py", "source_location": "L1", "weight": 1.0}, {"source": "watch_alert_service_rationale_57", "target": "watch_alert_service_watchalertservice_check_alerts", "relation": "rationale_for", "confidence": "EXTRACTED", "source_file": "app\\services\\watch_alert_service.py", "source_location": "L57", "weight": 1.0}, {"source": "watch_alert_service_rationale_214", "target": "watch_alert_service_watchalertservice_sr_detail", "relation": "rationale_for", "confidence": "EXTRACTED", "source_file": "app\\services\\watch_alert_service.py", "source_location": "L214", "weight": 1.0}]}